byunlp/__init__.py
byunlp/conjugate.py
byunlp-0.0.5.dist-info/METADATA
byunlp-0.0.5.dist-info/WHEEL
byunlp-0.0.5.dist-info/top_level.txt
byunlp-0.0.5.dist-info/RECORD
